flask_auto/__init__.py
flask_auto/create_flask_app.py
flask_auto-0.2.2.dist-info/LICENSE
flask_auto-0.2.2.dist-info/METADATA
flask_auto-0.2.2.dist-info/WHEEL
flask_auto-0.2.2.dist-info/entry_points.txt
flask_auto-0.2.2.dist-info/top_level.txt
flask_auto-0.2.2.dist-info/RECORD
