Metadata-Version: 2.1
Name: flask_auto
Version: 0.2.2
Summary: A simple Flask project generator
Home-page: https://github.com/ZeusPod/flask_auto
Author: Jose Luis Morales
Author-email: josseluism@gmail.com
Classifier: Programming Language :: Python :: 3
Classifier: License :: OSI Approved :: MIT License
Classifier: Operating System :: OS Independent
Requires-Python: >=3.6
License-File: LICENSE
Requires-Dist: Flask
Requires-Dist: Flask-SQLAlchemy
Requires-Dist: python-dotenv
Requires-Dist: psycopg2-binary
Requires-Dist: requests
